odoo10_addon_connector_lengow_amazon-10.0.1.0.0-py2.7-nspkg.pth
odoo/addons/connector_lengow_amazon/README.rst
odoo/addons/connector_lengow_amazon/__init__.py
odoo/addons/connector_lengow_amazon/__manifest__.py
odoo/addons/connector_lengow_amazon/models/__init__.py
odoo/addons/connector_lengow_amazon/models/configurator.py
odoo/addons/connector_lengow_amazon/tests/__init__.py
odoo/addons/connector_lengow_amazon/tests/test_lengow_stock.py
odoo10_addon_connector_lengow_amazon-10.0.1.0.0.dist-info/DESCRIPTION.rst
odoo10_addon_connector_lengow_amazon-10.0.1.0.0.dist-info/METADATA
odoo10_addon_connector_lengow_amazon-10.0.1.0.0.dist-info/RECORD
odoo10_addon_connector_lengow_amazon-10.0.1.0.0.dist-info/WHEEL
odoo10_addon_connector_lengow_amazon-10.0.1.0.0.dist-info/metadata.json
odoo10_addon_connector_lengow_amazon-10.0.1.0.0.dist-info/namespace_packages.txt
odoo10_addon_connector_lengow_amazon-10.0.1.0.0.dist-info/top_level.txt
